ox_script/__init__.py
ox_script/general_purpose_apis.py
ox_script/printer_specific_apis.py
ox_script-2.1.2.dist-info/METADATA
ox_script-2.1.2.dist-info/WHEEL
ox_script-2.1.2.dist-info/top_level.txt
ox_script-2.1.2.dist-info/RECORD
